{
  "faqs": [
    {
      "title": "Warum sehe keine Fotos im Fotoalbum?",
      "text": "Das Fotoalbum des Schwimmverein Haren e.V. dürfen nur von registrierte Benutzer angeschaut werden!"
    },
    {
      "title": "Was muss ich machen wenn ich Mitglied werden will?",
      "text": "Die genaue Infos zur Mitgliedschaft finden Sie hier."
    },
    {
      "title": "Was benötige ich für das Zeltlager (Packliste)?",
      "text": "Die Kleidung kann im Zeltlager auch einmal dreckig werden. Bitte daher nicht die neusten Sachen einpacken. Außerdem ist es hilfreich, wenn alle Sachen, soweit möglich und notwendig, mit Namen versehen sind, damit sie während des Zeltlagers zugeordnet werden können.\n\nFür das Zeltlager werden folgende Dinge benötigt:\n\n* Kleidung für 4 warme, nasse und kalte Tage\n* → 2 Pullover/ Sweatshirts\n* →  2 Fleece/dicke Pullover\n* →  3 T-Shirts\n* →  3 Lange Hosen\n* →  3 Kurze Hosen\n* 5 Unterhosen\n* 5 Unterhemden\n* 4 Paar Strümpfe\n* 1 Paar Halbschuhe\n* Evtl. 1 Paar Sandalen\n* 2 Paar feste Schuhe\n* Evtl. 1 Paar Gummistiefel\n* 1 Jacke\n* 1 Regenjacke\n* Kulturbeutel\n* → Waschlappen\n* → Seife\n* →  Zahnpasta\n* →  Zahnbürste\n* →  Evtl. Zahnspange und –behälter\n* → Bürste/ Kamm\n* → Haarshampoo\n* 3 Handtücher\n* Badehose/ Badeanzug\n* Sonnencreme\n* Schlafsachen\n* Schlafsack (evtl. zusätzliche Decke)\n* Matratze oder Feldbett\n* Kleiner Rucksack\n* Trinkflasche\n* Taschenlampe (evtl. Batterien)\n* Kuscheltier\n* Liederbücher/ Lesebuch\n* Spiele (z.B. Brett-/Kartenspiele; keine Nintendos, Handys etc.)\n* CD’s mit euren Lieblingsliedern\n* Teller und Becher (wenn möglich, aus Kunststoff)\n* Besteck\n* Geschirrtücher\n* Krankenkassenkarte (wird zu Beginn von uns Leitern eingesammelt)\n* Zelt (nach Absprache)\n* Ein kleines Taschengeld (5-10€)\n* Evtl. etwas Süßes oder Knabbersachen"
    }
  ]
}