{
  "news": [
    {
      "active": true,
      "title": "24h Schwimmen 2022",
      "body": "Es ist wieder soweit! Das 24h Schwimmen findet dieses Jahr wieder am 16./17. Dezember 2022 statt.",
      "href": ""
    },
    {
      "active": false,
      "title": "Google",
      "body": "Google hat neue News. Wenn du hier drauf klickst, öffnest du Google!",
      "href": "https://google.de"
    },
    {
      "active": true,
      "title": "Trainingsausfall",
      "body": "Am kommenden Montag den 45. Dezember 4444 fällt das Schwimmtraining aus! \ns sdf s sd\ns dfgsdfgsdfg\nsdf gs\ndf gsd\nf gsdfg\n sd\nfg sdf\ng sd\nfgsd f\ngsdfgs d\nf snhsdfgdf\ng sdf\n gsdfg\n sdfg\n sdfg\nsdfg\nsdfg\nsdfdg\nsdf g\nsdf gsdf  lkj sdf söldf sdöfl söflköflkjsdöflkjsdfölk jsdf söd lsödf ljksdöflgkj\ndfgsdflgsöldfk\n dfg\n sdfg\n sdf \n sfg s gsfgjh\n fgsdfgh sjdfgklgls khhg l lksdjhfglkj\n sdfghsdfkljghldfj\n slkjdghlkdfj  dfgsjhdfgljdhf jhd klsdjh lkj klsdflkgjhafl kjahglakjg\n\n sdjfgkdjfhglk\n\n dfgsjkghlkdfjh\n\n\n\n sdfjkgsdlfkjghldfkjghldj\ng",
      "href": "https://schwimmverein-haren.de/index.php?id=105"
    },
    {
      "active": true,
      "title": "Vereinsmeisterschat",
      "body": "Am 4. März 5677 findet unser nächtes Vereinsmeisterschaft statt. Bitte den Termin schon vormerken !"
    }
  ]
}